uwcwidth-1.0.0.dist-info/RECORD
uwcwidth-1.0.0.dist-info/LICENSE
uwcwidth-1.0.0.dist-info/WHEEL
uwcwidth-1.0.0.dist-info/top_level.txt
uwcwidth-1.0.0.dist-info/METADATA
uwcwidth/uwcwidth.pyx
uwcwidth/__init__.pxd
uwcwidth/__init__.py
uwcwidth/tables.pxd
uwcwidth/uwcwidth.cpython-312-darwin.so
uwcwidth/uwcwidth.pxd
