Metadata-Version: 2.1
Name: uwcwidth
Version: 1.0.0
Summary: terminal width of Unicode 16.0+Emoji strings in nanoseconds
Author: !ZAJC!
License: MIT License
Project-URL: Homepage, https://github.com/Z4JC/uwcwidth
Classifier: Development Status :: 5 - Production/Stable
Classifier: Intended Audience :: Developers
Classifier: License :: OSI Approved :: MIT License
Classifier: Programming Language :: Python :: 3
Classifier: Topic :: Software Development :: Libraries :: Python Modules
Classifier: Topic :: Software Development :: Localization
Classifier: Topic :: Software Development :: Internationalization
Classifier: Topic :: Terminals
License-File: LICENSE
Provides-Extra: test
Requires-Dist: pytest ; extra == 'test'
